t3/__init__.py
t3/_version.py
t3/env.py
t3/log.py
t3/util.py
t3/django/__init__.py
t3/django/log.py
t3/django/models.py
t3/django/settings.py
t3/django/storages.py
t3/django/urls.py
t3/django/util.py
t3/django/requests/__init__.py
t3/django/requests/cache.py
t3/django/requests/concurrent.py
t3/django/requests/retry.py
t3/drf/__init__.py
t3/drf/settings.py
t3/drf/urls.py
t3/drf/views.py
t3/drf_adapters/__init__.py
t3/drf_adapters/exceptions.py
t3/drf_adapters/mixins.py
t3/drf_adapters/resources.py
t3/drf_adapters/serializers.py
t3/drf_adapters/viewsets.py
t3/events/__init__.py
t3/events/base_consumer.py
t3/events/base_publisher.py
t3/events/consumers.py
t3/events/publishers.py
t3/events/util.py
t3/vendors/__init__.py
t3/vendors/google_recaptcha.py
t3/vendors/punchh.py
tests/__init__.py
tests/test_smoke.py
tests/django/__init__.py
tests/django/test_urls.py
t3_core-0.11.5.dist-info/METADATA
t3_core-0.11.5.dist-info/WHEEL
t3_core-0.11.5.dist-info/top_level.txt
t3_core-0.11.5.dist-info/RECORD
