Metadata-Version: 2.1
Name: t3-core
Version: 0.11.5
Summary: Boilerplate to quickly setup a Django Rest Framework Microservice for T3
Home-page: https://www.t-3.com/
Author: Travis Krause
Author-email: travis.krause@t-3.com
License: UNKNOWN
Keywords: t3 t3-python-core
Platform: UNKNOWN
Classifier: Development Status :: 2 - Pre-Alpha
Classifier: Intended Audience :: Developers
Classifier: Operating System :: OS Independent
Classifier: Natural Language :: English
Classifier: Programming Language :: Python :: 3.6
Requires-Dist: Django (==2.2.4)
Requires-Dist: gunicorn (==19.9.0)
Requires-Dist: psycopg2-binary (==2.7.5)
Requires-Dist: djangorestframework (==3.9.0)
Requires-Dist: django-filter (==2.0.0)
Requires-Dist: markdown (==2.6.11)
Requires-Dist: coreapi (==2.3.3)
Requires-Dist: django-crispy-forms (==1.7.2)
Requires-Dist: drf-yasg[validation] (==1.11.0)
Requires-Dist: django-extensions (==2.1.2)
Requires-Dist: django-log-request-id (==1.3.2)
Requires-Dist: django-cors-headers (==2.4.0)
Requires-Dist: djangorestframework-camel-case (==0.2.0)
Requires-Dist: drf-nested-routers (==0.91)
Requires-Dist: boto3 (==1.9.6)
Requires-Dist: django-storages (==1.7.1)
Requires-Dist: watchtower (==0.5.3)
Requires-Dist: django-prometheus (==1.0.15)
Requires-Dist: requests (==2.19.1)
Requires-Dist: requests-oauthlib (==1.0.0)
Requires-Dist: python-dotenv[cli] (==0.9.1)
Requires-Dist: pygments (==2.2.0)
Requires-Dist: ipython[notebook] (==7.0.1)
Requires-Dist: PyYAML (==3.13)
Requires-Dist: PyJWT (==1.6.4)
Requires-Dist: coverage (==4.5.1)
Requires-Dist: pytest (==3.8.0)
Requires-Dist: pytest-cov (==2.6.0)
Requires-Dist: pytest-django (==3.4.3)
Requires-Dist: pytest-dotenv (==0.2.0)
Requires-Dist: pylint (==2.1.1)
Requires-Dist: pylint-django (==2.0.2)
Requires-Dist: pep8 (==1.7.1)
Requires-Dist: autopep8 (==1.4.1)
Requires-Dist: pylama (==7.6.5)
Requires-Dist: pylama-pylint (==3.1.1)
Requires-Dist: astroid (==2.0.4)
Requires-Dist: m2r (==0.2.0)
Requires-Dist: redis (==2.10.6)
Requires-Dist: cachecontrol (==0.12.6)
Requires-Dist: urllib3 (==1.23)
Requires-Dist: pika (==0.12.0)
Requires-Dist: click (==6.7)
